skala_lab_package/Decay_feature.py
skala_lab_package/Optimal_Transport.py
skala_lab_package/PCA_analysis.py
skala_lab_package/__init__.py
skala_lab_package/csv_maker.py
skala_lab_package/sdt_reading.py
skala_lab_package-0.1.7.dist-info/METADATA
skala_lab_package-0.1.7.dist-info/WHEEL
skala_lab_package-0.1.7.dist-info/top_level.txt
skala_lab_package-0.1.7.dist-info/RECORD
