Metadata-Version: 2.4
Name: skala_lab_package
Version: 0.1.7
Summary: A package for redox feature analysis, CSV generation, and SDT file handling.
Home-page: https://github.com/monatopotato
Author: Manato Ogawa
Author-email: maogawa@wisc.edu
Classifier: Programming Language :: Python :: 3
Classifier: License :: OSI Approved :: MIT License
Classifier: Operating System :: OS Independent
Requires-Python: >=3.8
Requires-Dist: numpy
Dynamic: author
Dynamic: author-email
Dynamic: classifier
Dynamic: description
Dynamic: description-content-type
Dynamic: home-page
Dynamic: requires-dist
Dynamic: requires-python
Dynamic: summary
